{
  "metadata": {
    "data_version": "6",
    "match_id": "NA1_5411880024",
    "participants": [
      "bqqdRQwwmssgE6ZzPrikVXbnajVF15yI2LJ9FMia1U-EnN7eQICB6wRSefIthh7NZOZQm3-zWntE1Q",
      "vcOJJgpd0Eig0iM6PQq3ROpE3texg2CQ4L6xNtRsJXJ9Q1LwBwB_WkudYjSBwhE8Ld9tNJnFbldr_A",
      "MmDI1S8qqYYfQciEmtLGVSfsJrNQjv9KcMKmOyhbSvl4dTdKN4D8eE4YP8YKXGe9GEMFqGOFkAiZow",
      "nVetCOkR7g2L4MYA5GCthGdbeXT4p9Po790b2txuZKgwzViXxPbWR2PfTbt5Egfb0T6bV-Jv9c8CHw",
      "5nReJb_YLuOohavOHkgrZ_yYmXJH6GB0eYjfFoSkToBmg2fBB3w5LlPF7Mwyt-l5qT2NDZqAopKkRA",
      "1TNdxZjXcSRPwW2zR6dqWgauhfbEnNfpKSZblSWvT6jP655tLAWo4xl1VGFZ0Y0uOiX0nSy6IQKoOg",
      "rRoCKq_jHvuKdbUgLxulklRGjJsvOebx5PsLWK8GH6MR3hTpvD5w17cu7MKkUeUFu0aylqHJyJDsqA",
      "Fch2j9cXT8lmqdnDmWd5An0m6-3zbUoAxNYhfF_jLk5xKEZ3bueretuZdFtqtY-WBmP3HJGgEbuMNg"
    ]
  },
  "info": {
    "endOfGameResult": "GameComplete",
    "gameCreation": 1762934268000,
    "gameId": 5411880024,
    "game_datetime": 1762936492470,
    "game_length": 2206.901123046875,
    "game_version": "Linux Version 15.22.724.5161 (Nov 05 2025/16:11:29) [PUBLIC] <Releases/15.22>",
    "mapId": 22,
    "participants": [
      {
        "companion": {
          "content_ID": "f130db9f-a102-4dac-be13-e332adb942ff",
          "item_ID": 79004,
          "skin_ID": 4,
          "species": "PetChibiYone"
        },
        "gold_left": 2,
        "last_round": 28,
        "level": 8,
        "missions": {
          "PlayerScore2": 81
        },
        "placement": 7,
        "players_eliminated": 0,
        "puuid": "bqqdRQwwmssgE6ZzPrikVXbnajVF15yI2LJ9FMia1U-EnN7eQICB6wRSefIthh7NZOZQm3-zWntE1Q",
        "riotIdGameName": "ChoppedTimbs",
        "riotIdTagline": "RyanL",
        "time_eliminated": 1615.9615478515625,
        "total_damage_to_players": 69,
        "traits": [
          {
            "name": "TFT15_Bastion",
            "num_units": 1,
            "style": 0,
            "tier_current": 0,
            "tier_total": 3
          },
          {
            "name": "TFT15_Duelist",
            "num_units": 2,
            "style": 1,
            "tier_current": 1,
            "tier_total": 3
          },
          {
            "name": "TFT15_Empyrean",
            "num_units": 1,
            "style": 0,
            "tier_current": 0,
            "tier_total": 3
          },
          {
            "name": "TFT15_GemForce",
            "num_units": 4,
            "style": 1,
            "tier_current": 1,
            "tier_total": 4
          },
          {
            "name": "TFT15_Juggernaut",
            "num_units": 2,
            "style": 1,
            "tier_current": 1,
            "tier_total": 3
          },
          {
            "name": "TFT15_OldMentor",
            "num_units": 1,
            "style": 1,
            "tier_current": 1,
            "tier_total": 3
          },
          {
            "name": "TFT15_Prodigy",
            "num_units": 1,
            "style": 0,
            "tier_current": 0,
            "tier_total": 4
          },
          {
            "name": "TFT15_Protector",
            "num_units": 2,
            "style": 1,
            "tier_current": 1,
            "tier_total": 3
          },
          {
            "name": "TFT15_SentaiRanger",
            "num_units": 1,
            "style": 0,
            "tier_current": 0,
            "tier_total": 4
          },
          {
            "name": "TFT15_SoulFighter",
            "num_units": 1,
            "style": 0,
            "tier_current": 0,
            "tier_total": 5
          },
          {
            "name": "TFT15_StarGuardian",
            "num_units": 1,
            "style": 0,
            "tier_current": 0,
            "tier_total": 12
          },
          {
            "name": "TFT15_Strategist",
            "num_units": 2,
            "style": 1,
            "tier_current": 1,
            "tier_total": 4
          }
        ],
        "units": [
          {
            "character_id": "TFT15_Syndra",
            "itemNames": [],
            "name": "",
            "rarity": 0,
            "tier": 2
          },
          {
            "character_id": "TFT15_XinZhao",
            "itemNames": [],
            "name": "",
            "rarity": 1,
            "tier": 1
          },
          {
            "character_id": "TFT15_Vi",
            "itemNames": [
              "TFT_Item_InfinityEdge",
              "TFT_Item_UnstableConcoction",
              "TFT_Item_Bloodthirster"
            ],
            "name": "",
            "rarity": 1,
            "tier": 2
          },
          {
            "character_id": "TFT15_Janna",
            "itemNames": [],
            "name": "",
            "rarity": 1,
            "tier": 2
          },
          {
            "character_id": "TFT15_Udyr",
            "itemNames": [],
            "name": "",
            "rarity": 2,
            "tier": 1
          },
          {
            "character_id": "TFT15_Ashe",
            "itemNames": [
              "TFT_Item_LastWhisper",
              "TFT_Item_RunaansHurricane",
              "TFT_Item_GuinsoosRageblade"
            ],
            "name": "",
            "rarity": 4,
            "tier": 2
          },
          {
            "character_id": "TFT15_KSante",
            "itemNames": [
              "TFT_Item_IonicSpark"
            ],
            "name": "",
            "rarity": 4,
            "tier": 1
          },
          {
            "character_id": "TFT15_JarvanIV",
            "itemNames": [
              "TFT_Item_BrambleVest",
              "TFT_Item_DragonsClaw",
              "TFT_Item_Redemption"
            ],
            "name": "",
            "rarity": 4,
            "tier": 2
          }
        ],
        "win": false
      },
      {
        "companion": {
          "content_ID": "5897ad9f-4665-4372-8f3e-6c878adb8918",
          "item_ID": 1,
          "skin_ID": 1,
          "species": "PetTFTAvatar"
        },
        "gold_left": 1,
        "last_round": 26,
        "level": 8,
        "missions": {
          "PlayerScore2": 74
        },
        "placement": 8,
        "players_eliminated": 0,
        "puuid": "vcOJJgpd0Eig0iM6PQq3ROpE3texg2CQ4L6xNtRsJXJ9Q1LwBwB_WkudYjSBwhE8Ld9tNJnFbldr_A",
        "riotIdGameName": "PapyNA",
        "riotIdTagline": "NA1",
        "time_eliminated": 1491.328369140625,
        "total_damage_to_players": 41,
        "traits": [
          {
            "name": "TFT15_Bastion",
            "num_units": 2,
            "style": 1,
            "tier_current": 1,
            "tier_total": 3
          },
          {
            "name": "TFT15_Duelist",
            "num_units": 2,
            "style": 1,
            "tier_current": 1,
            "tier_total": 3
          },
          {
            "name": "TFT15_ElTigre",
            "num_units": 1,
            "style": 3,
            "tier_current": 1,
            "tier_total": 1
          },
          {
            "name": "TFT15_GemForce",
            "num_units": 5,
            "style": 4,
            "tier_current": 2,
            "tier_total": 4
          },
          {
            "name": "TFT15_Juggernaut",
            "num_units": 2,
            "style": 1,
            "tier_current": 1,
            "tier_total": 3
          },
          {
            "name": "TFT15_Luchador",
            "num_units": 1,
            "style": 0,
            "tier_current": 0,
            "tier_total": 2
          },
          {
            "name": "TFT15_OldMentor",
            "num_units": 1,
            "style": 1,
            "tier_current": 1,
            "tier_total": 3
          },
          {
            "name": "TFT15_Protector",
            "num_units": 1,
            "style": 0,
            "tier_current": 0,
            "tier_total": 3
          },
          {
            "name": "TFT15_Rosemother",
            "num_units": 1,
            "style": 3,
            "tier_current": 1,
            "tier_total": 1
          },
          {
            "name": "TFT15_SentaiRanger",
            "num_units": 1,
            "style": 0,
            "tier_current": 0,
            "tier_total": 4
          },
          {
            "name": "TFT15_Spellslinger",
            "num_units": 1,
            "style": 0,
            "tier_current": 0,
            "tier_total": 3
          },
          {
            "name": "TFT15_Strategist",
            "num_units": 2,
            "style": 1,
            "tier_current": 1,
            "tier_total": 4
          }
        ],
        "units": [
          {
            "character_id": "TFT15_Vi",
            "itemNames": [],
            "name": "",
            "rarity": 1,
            "tier": 2
          },
          {
            "character_id": "TFT15_Janna",
            "itemNames": [],
            "name": "",
            "rarity": 1,
            "tier": 2
          },
          {
            "character_id": "TFT15_Swain",
            "itemNames": [
              "TFT_Item_RedBuff",
              "TFT_Item_Redemption",
              "TFT_Item_SteraksGage"
            ],
            "name": "",
            "rarity": 2,
            "tier": 2
          },
          {
            "character_id": "TFT15_Udyr",
            "itemNames": [],
            "name": "",
            "rarity": 2,
            "tier": 2
          },
          {
            "character_id": "TFT15_Ashe",
            "itemNames": [
              "TFT_Item_MadredsBloodrazor",
              "TFT_Item_RunaansHurricane",
              "TFT_Item_GuinsoosRageblade"
            ],
            "name": "",
            "rarity": 4,
            "tier": 1
          },
          {
            "character_id": "TFT15_JarvanIV",
            "itemNames": [
              "TFT_Item_Crownguard"
            ],
            "name": "",
            "rarity": 4,
            "tier": 1
          },
          {
            "character_id": "TFT15_Braum",
            "itemNames": [
              "TFT_Item_ThiefsGloves",
              "TFT_Item_SteraksGage",
              "TFT_Item_Bloodthirster"
            ],
            "name": "",
            "rarity": 6,
            "tier": 1
          },
          {
            "character_id": "TFT15_Zyra",
            "itemNames": [
              "TFT_Item_ThiefsGloves",
              "TFT_Item_DragonsClaw",
              "TFT_Item_HextechGunblade"
            ],
            "name": "",
            "rarity": 6,
            "tier": 1
          }
        ],
        "win": false
      },
      {
        "companion": {
          "content_ID": "7afd5ce8-db04-43fa-a76b-ff0dc9c3d1ec",
          "item_ID": 52023,
          "skin_ID": 23,
          "species": "PetBunny"
        },
        "gold_left": 4,
        "last_round": 38,
        "level": 9,
        "missions": {
          "PlayerScore2": 219
        },
        "placement": 1,
        "players_eliminated": 2,
        "puuid": "MmDI1S8qqYYfQciEmtLGVSfsJrNQjv9KcMKmOyhbSvl4dTdKN4D8eE4YP8YKXGe9GEMFqGOFkAiZow",
        "riotIdGameName": "Portuguese Babe",
        "riotIdTagline": "NA82",
        "time_eliminated": 2198.690185546875,
        "total_damage_to_players": 182,
        "traits": [
          {
            "name": "TFT15_Bastion",
            "num_units": 2,
            "style": 1,
            "tier_current": 1,
            "tier_total": 3
          },
          {
            "name": "TFT15_ElTigre",
            "num_units": 1,
            "style": 3,
            "tier_current": 1,
            "tier_total": 1
          },
          {
            "name": "TFT15_Empyrean",
            "num_units": 1,
            "style": 0,
            "tier_current": 0,
            "tier_total": 3
          },
          {
            "name": "TFT15_GemForce",
            "num_units": 1,
            "style": 0,
            "tier_current": 0,
            "tier_total": 4
          },
          {
            "name": "TFT15_Heavyweight",
            "num_units": 2,
            "style": 1,
            "tier_current": 1,
            "tier_total": 3
          },
          {
            "name": "TFT15_Luchador",
            "num_units": 1,
            "style": 0,
            "tier_current": 0,
            "tier_total": 2
          },
          {
            "name": "TFT15_OldMentor",
            "num_units": 1,
            "style": 1,
            "tier_current": 1,
            "tier_total": 3
          },
          {
            "name": "TFT15_Prodigy",
            "num_units": 2,
            "style": 1,
            "tier_current": 1,
            "tier_total": 4
          },
          {
            "name": "TFT15_Protector",
            "num_units": 2,
            "style": 1,
            "tier_current": 1,
            "tier_total": 3
          },
          {
            "name": "TFT15_Sniper",
            "num_units": 1,
            "style": 0,
            "tier_current": 0,
            "tier_total": 4
          },
          {
            "name": "TFT15_StarGuardian",
            "num_units": 7,
            "style": 4,
            "tier_current": 6,
            "tier_total": 12
          }
        ],
        "units": [
          {
            "character_id": "TFT15_Rell",
            "itemNames": [
              "TFT_Item_NegatronCloak"
            ],
            "name": "",
            "rarity": 0,
            "tier": 2
          },
          {
            "character_id": "TFT15_Syndra",
            "itemNames": [],
            "name": "",
            "rarity": 0,
            "tier": 2
          },
          {
            "character_id": "TFT15_Kobuko",
            "itemNames": [],
            "name": "",
            "rarity": 1,
            "tier": 2
          },
          {
            "character_id": "TFT15_Neeko",
            "itemNames": [],
            "name": "",
            "rarity": 2,
            "tier": 2
          },
          {
            "character_id": "TFT15_Jinx",
            "itemNames": [
              "TFT_Item_SpearOfShojin",
              "TFT_Item_MadredsBloodrazor",
              "TFT_Item_InfinityEdge"
            ],
            "name": "",
            "rarity": 4,
            "tier": 2
          },
          {
            "character_id": "TFT15_KSante",
            "itemNames": [
              "TFT15_Item_StarGuardianEmblemItem",
              "TFT_Item_GargoyleStoneplate",
              "TFT_Item_TitansResolve"
            ],
            "name": "",
            "rarity": 4,
            "tier": 2
          },
          {
            "character_id": "TFT15_Poppy",
            "itemNames": [
              "TFT_Item_AdaptiveHelm",
              "TFT_Item_WarmogsArmor",
              "TFT_Item_AdaptiveHelm"
            ],
            "name": "",
            "rarity": 4,
            "tier": 2
          },
          {
            "character_id": "TFT15_Braum",
            "itemNames": [
              "TFT_Item_ThiefsGloves",
              "TFT_Item_RapidFireCannon",
              "TFT_Item_BlueBuff"
            ],
            "name": "",
            "rarity": 6,
            "tier": 2
          },
          {
            "character_id": "TFT15_Seraphine",
            "itemNames": [
              "TFT_Item_LastWhisper",
              "TFT_Item_RapidFireCannon",
              "TFT_Item_InfinityEdge"
            ],
            "name": "",
            "rarity": 6,
            "tier": 2
          }
        ],
        "win": true
      },
      {
        "companion": {
          "content_ID": "51e12c33-bf9a-4cd7-b619-36fe636952ee",
          "item_ID": 44001,
          "skin_ID": 1,
          "species": "PetChibiLeeSin"
        },
        "gold_left": 0,
        "last_round": 34,
        "level": 8,
        "missions": {
          "PlayerScore2": 196
        },
        "placement": 4,
        "players_eliminated": 0,
        "puuid": "nVetCOkR7g2L4MYA5GCthGdbeXT4p9Po790b2txuZKgwzViXxPbWR2PfTbt5Egfb0T6bV-Jv9c8CHw",
        "riotIdGameName": "ChiBixSlAde444",
        "riotIdTagline": "NA1",
        "time_eliminated": 1966.2518310546875,
        "total_damage_to_players": 114,
        "traits": [
          {
            "name": "TFT15_Bastion",
            "num_units": 1,
            "style": 0,
            "tier_current": 0,
            "tier_total": 3
          },
          {
            "name": "TFT15_Duelist",
            "num_units": 2,
            "style": 1,
            "tier_current": 1,
            "tier_total": 3
          },
          {
            "name": "TFT15_Edgelord",
            "num_units": 2,
            "style": 1,
            "tier_current": 1,
            "tier_total": 3
          },
          {
            "name": "TFT15_Juggernaut",
            "num_units": 2,
            "style": 1,
            "tier_current": 1,
            "tier_total": 3
          },
          {
            "name": "TFT15_Luchador",
            "num_units": 1,
            "style": 0,
            "tier_current": 0,
            "tier_total": 2
          },
          {
            "name": "TFT15_OldMentor",
            "num_units": 1,
            "style": 1,
            "tier_current": 1,
            "tier_total": 3
          },
          {
            "name": "TFT15_SoulFighter",
            "num_units": 6,
            "style": 2,
            "tier_current": 3,
            "tier_total": 5
          },
          {
            "name": "TFT15_Spellslinger",
            "num_units": 2,
            "style": 1,
            "tier_current": 1,
            "tier_total": 3
          }
        ],
        "units": [
          {
            "character_id": "TFT15_Lux",
            "itemNames": [],
            "name": "",
            "rarity": 1,
            "tier": 2
          },
          {
            "character_id": "TFT15_XinZhao",
            "itemNames": [],
            "name": "",
            "rarity": 1,
            "tier": 2
          },
          {
            "character_id": "TFT15_Udyr",
            "itemNames": [],
            "name": "",
            "rarity": 2,
            "tier": 2
          },
          {
            "character_id": "TFT15_Viego",
            "itemNames": [
              "TFT_Item_GuardianAngel"
            ],
            "name": "",
            "rarity": 2,
            "tier": 2
          },
          {
            "character_id": "TFT15_Samira",
            "itemNames": [
              "TFT_Item_Deathblade",
              "TFT_Item_MadredsBloodrazor",
              "TFT_Item_BlueBuff"
            ],
            "name": "",
            "rarity": 4,
            "tier": 2
          },
          {
            "character_id": "TFT15_Sett",
            "itemNames": [
              "TFT_Item_FrozenHeart",
              "TFT_Item_SpectralGauntlet",
              "TFT_Item_NightHarvester"
            ],
            "name": "",
            "rarity": 4,
            "tier": 2
          },
          {
            "character_id": "TFT15_Volibear",
            "itemNames": [
              "TFT_Item_TitansResolve",
              "TFT_Item_SteraksGage",
              "TFT_Item_SteraksGage"
            ],
            "name": "",
            "rarity": 4,
            "tier": 2
          },
          {
            "character_id": "TFT15_Gwen",
            "itemNames": [
              "TFT_Item_ThiefsGloves",
              "TFT_Item_GuinsoosRageblade",
              "TFT_Item_SteraksGage"
            ],
            "name": "",
            "rarity": 6,
            "tier": 2
          },
          {
            "character_id": "TFT15_Volibear",
            "itemNames": [],
            "name": "",
            "rarity": 4,
            "tier": 2
          }
        ],
        "win": true
      },
      {
        "companion": {
          "content_ID": "25b1326b-341a-4e36-a175-1d39872231bd",
          "item_ID": 66007,
          "skin_ID": 7,
          "species": "PetPoro"
        },
        "gold_left": 8,
        "last_round": 34,
        "level": 9,
        "missions": {
          "PlayerScore2": 196
        },
        "placement": 3,
        "players_eliminated": 2,
        "puuid": "5nReJb_YLuOohavOHkgrZ_yYmXJH6GB0eYjfFoSkToBmg2fBB3w5LlPF7Mwyt-l5qT2NDZqAopKkRA",
        "riotIdGameName": "Alanwhere",
        "riotIdTagline": "3635",
        "time_eliminated": 1967.6036376953125,
        "total_damage_to_players": 99,
        "traits": [
          {
            "name": "TFT15_BattleAcademia",
            "num_units": 1,
            "style": 0,
            "tier_current": 0,
            "tier_total": 4
          },
          {
            "name": "TFT15_Duelist",
            "num_units": 1,
            "style": 0,
            "tier_current": 0,
            "tier_total": 3
          },
          {
            "name": "TFT15_Empyrean",
            "num_units": 4,
            "style": 2,
            "tier_current": 2,
            "tier_total": 3
          },
          {
            "name": "TFT15_Heavyweight",
            "num_units": 6,
            "style": 4,
            "tier_current": 3,
            "tier_total": 3
          },
          {
            "name": "TFT15_Juggernaut",
            "num_units": 1,
            "style": 0,
            "tier_current": 0,
            "tier_total": 3
          },
          {
            "name": "TFT15_OldMentor",
            "num_units": 1,
            "style": 1,
            "tier_current": 1,
            "tier_total": 3
          },
          {
            "name": "TFT15_Prodigy",
            "num_units": 1,
            "style": 0,
            "tier_current": 0,
            "tier_total": 4
          },
          {
            "name": "TFT15_Protector",
            "num_units": 1,
            "style": 0,
            "tier_current": 0,
            "tier_total": 3
          },
          {
            "name": "TFT15_SentaiRanger",
            "num_units": 1,
            "style": 0,
            "tier_current": 0,
            "tier_total": 4
          },
          {
            "name": "TFT15_StarGuardian",
            "num_units": 1,
            "style": 0,
            "tier_current": 0,
            "tier_total": 12
          },
          {
            "name": "TFT15_SupremeCells",
            "num_units": 1,
            "style": 0,
            "tier_current": 0,
            "tier_total": 3
          }
        ],
        "units": [
          {
            "character_id": "TFT15_Kayle",
            "itemNames": [
              "TFT_Item_MadredsBloodrazor",
              "TFT_Item_GuinsoosRageblade",
              "TFT_Item_PowerGauntlet"
            ],
            "name": "",
            "rarity": 0,
            "tier": 2
          },
          {
            "character_id": "TFT15_Zac",
            "itemNames": [
              "TFT_Item_Bloodthirster",
              "TFT_Item_GuardianAngel",
              "TFT_Item_JeweledGauntlet"
            ],
            "name": "",
            "rarity": 0,
            "tier": 3
          },
          {
            "character_id": "TFT15_Aatrox",
            "itemNames": [],
            "name": "",
            "rarity": 0,
            "tier": 2
          },
          {
            "character_id": "TFT15_Kobuko",
            "itemNames": [],
            "name": "",
            "rarity": 1,
            "tier": 2
          },
          {
            "character_id": "TFT15_Darius",
            "itemNames": [],
            "name": "",
            "rarity": 2,
            "tier": 2
          },
          {
            "character_id": "TFT15_Malzahar",
            "itemNames": [
              "TFT_Item_Morellonomicon"
            ],
            "name": "",
            "rarity": 2,
            "tier": 1
          },
          {
            "character_id": "TFT15_Jayce",
            "itemNames": [],
            "name": "",
            "rarity": 2,
            "tier": 2
          },
          {
            "character_id": "TFT15_KSante",
            "itemNames": [],
            "name": "",
            "rarity": 4,
            "tier": 1
          },
          {
            "character_id": "TFT15_Poppy",
            "itemNames": [
              "TFT_Item_FrozenHeart",
              "TFT_Item_DragonsClaw",
              "TFT_Item_WarmogsArmor"
            ],
            "name": "",
            "rarity": 4,
            "tier": 1
          }
        ],
        "win": true
      },
      {
        "companion": {
          "content_ID": "bf219e7b-66f8-417e-8208-c867ccdcb10c",
          "item_ID": 74001,
          "skin_ID": 1,
          "species": "PetChibiIrelia"
        },
        "gold_left": 1,
        "last_round": 33,
        "level": 9,
        "missions": {
          "PlayerScore2": 95
        },
        "placement": 5,
        "players_eliminated": 0,
        "puuid": "1TNdxZjXcSRPwW2zR6dqWgauhfbEnNfpKSZblSWvT6jP655tLAWo4xl1VGFZ0Y0uOiX0nSy6IQKoOg",
        "riotIdGameName": "poison heart UU",
        "riotIdTagline": "NA1",
        "time_eliminated": 1900.6983642578125,
        "total_damage_to_players": 92,
        "traits": [
          {
            "name": "TFT15_Duelist",
            "num_units": 2,
            "style": 1,
            "tier_current": 1,
            "tier_total": 3
          },
          {
            "name": "TFT15_Empyrean",
            "num_units": 6,
            "style": 4,
            "tier_current": 3,
            "tier_total": 3
          },
          {
            "name": "TFT15_Heavyweight",
            "num_units": 2,
            "style": 1,
            "tier_current": 1,
            "tier_total": 3
          },
          {
            "name": "TFT15_Juggernaut",
            "num_units": 1,
            "style": 0,
            "tier_current": 0,
            "tier_total": 3
          },
          {
            "name": "TFT15_OldMentor",
            "num_units": 1,
            "style": 1,
            "tier_current": 1,
            "tier_total": 3
          },
          {
            "name": "TFT15_Prodigy",
            "num_units": 1,
            "style": 0,
            "tier_current": 0,
            "tier_total": 4
          },
          {
            "name": "TFT15_Protector",
            "num_units": 2,
            "style": 1,
            "tier_current": 1,
            "tier_total": 3
          },
          {
            "name": "TFT15_Sniper",
            "num_units": 2,
            "style": 1,
            "tier_current": 1,
            "tier_total": 4
          },
          {
            "name": "TFT15_StarGuardian",
            "num_units": 2,
            "style": 1,
            "tier_current": 1,
            "tier_total": 12
          }
        ],
        "units": [
          {
            "character_id": "TFT15_Kayle",
            "itemNames": [
              "TFT_Item_MadredsBloodrazor",
              "TFT_Item_JeweledGauntlet",
              "TFT_Item_Quicksilver"
            ],
            "name": "",
            "rarity": 0,
            "tier": 3
          },
          {
            "character_id": "TFT15_Zac",
            "itemNames": [],
            "name": "",
            "rarity": 0,
            "tier": 2
          },
          {
            "character_id": "TFT15_Jhin",
            "itemNames": [],
            "name": "",
            "rarity": 1,
            "tier": 1
          },
          {
            "character_id": "TFT15_Malzahar",
            "itemNames": [],
            "name": "",
            "rarity": 2,
            "tier": 2
          },
          {
            "character_id": "TFT15_Udyr",
            "itemNames": [],
            "name": "",
            "rarity": 2,
            "tier": 2
          },
          {
            "character_id": "TFT15_Neeko",
            "itemNames": [],
            "name": "",
            "rarity": 2,
            "tier": 2
          },
          {
            "character_id": "TFT15_KSante",
            "itemNames": [
              "TFT_Item_RedBuff",
              "TFT_Item_Redemption",
              "TFT_Item_Crownguard"
            ],
            "name": "",
            "rarity": 4,
            "tier": 2
          },
          {
            "character_id": "TFT15_Poppy",
            "itemNames": [
              "TFT_Item_GiantsBelt"
            ],
            "name": "",
            "rarity": 4,
            "tier": 1
          },
          {
            "character_id": "TFT15_Varus",
            "itemNames": [
              "TFT_Item_GuardianAngel",
              "TFT_Item_AdaptiveHelm",
              "TFT_Item_HextechGunblade"
            ],
            "name": "",
            "rarity": 6,
            "tier": 2
          },
          {
            "character_id": "TFT15_Kayle",
            "itemNames": [
              "TFT_Item_MadredsBloodrazor",
              "TFT_Item_JeweledGauntlet",
              "TFT_Item_Quicksilver"
            ],
            "name": "",
            "rarity": 0,
            "tier": 3
          },
          {
            "character_id": "TFT15_KSante",
            "itemNames": [],
            "name": "",
            "rarity": 4,
            "tier": 2
          }
        ],
        "win": false
      },
      {
        "companion": {
          "content_ID": "51308483-ce6c-49e7-9727-aa300827016f",
          "item_ID": 4001,
          "skin_ID": 1,
          "species": "PetMiner"
        },
        "gold_left": 3,
        "last_round": 28,
        "level": 9,
        "missions": {
          "PlayerScore2": 81
        },
        "placement": 6,
        "players_eliminated": 0,
        "puuid": "rRoCKq_jHvuKdbUgLxulklRGjJsvOebx5PsLWK8GH6MR3hTpvD5w17cu7MKkUeUFu0aylqHJyJDsqA",
        "riotIdGameName": "afar",
        "riotIdTagline": "NA1",
        "time_eliminated": 1627.1060791015625,
        "total_damage_to_players": 64,
        "traits": [
          {
            "name": "TFT15_Bastion",
            "num_units": 2,
            "style": 1,
            "tier_current": 1,
            "tier_total": 3
          },
          {
            "name": "TFT15_DragonFist",
            "num_units": 1,
            "style": 3,
            "tier_current": 1,
            "tier_total": 1
          },
          {
            "name": "TFT15_Duelist",
            "num_units": 2,
            "style": 1,
            "tier_current": 1,
            "tier_total": 3
          },
          {
            "name": "TFT15_ElTigre",
            "num_units": 1,
            "style": 3,
            "tier_current": 1,
            "tier_total": 1
          },
          {
            "name": "TFT15_Empyrean",
            "num_units": 1,
            "style": 0,
            "tier_current": 0,
            "tier_total": 3
          },
          {
            "name": "TFT15_GemForce",
            "num_units": 5,
            "style": 4,
            "tier_current": 2,
            "tier_total": 4
          },
          {
            "name": "TFT15_Juggernaut",
            "num_units": 2,
            "style": 1,
            "tier_current": 1,
            "tier_total": 3
          },
          {
            "name": "TFT15_Luchador",
            "num_units": 1,
            "style": 0,
            "tier_current": 0,
            "tier_total": 2
          },
          {
            "name": "TFT15_Protector",
            "num_units": 2,
            "style": 1,
            "tier_current": 1,
            "tier_total": 3
          },
          {
            "name": "TFT15_Rosemother",
            "num_units": 1,
            "style": 3,
            "tier_current": 1,
            "tier_total": 1
          },
          {
            "name": "TFT15_SentaiRanger",
            "num_units": 1,
            "style": 0,
            "tier_current": 0,
            "tier_total": 4
          },
          {
            "name": "TFT15_Spellslinger",
            "num_units": 1,
            "style": 0,
            "tier_current": 0,
            "tier_total": 3
          },
          {
            "name": "TFT15_Strategist",
            "num_units": 2,
            "style": 1,
            "tier_current": 1,
            "tier_total": 4
          }
        ],
        "units": [
          {
            "character_id": "TFT15_Vi",
            "itemNames": [],
            "name": "",
            "rarity": 1,
            "tier": 2
          },
          {
            "character_id": "TFT15_Janna",
            "itemNames": [],
            "name": "",
            "rarity": 1,
            "tier": 2
          },
          {
            "character_id": "TFT15_Swain",
            "itemNames": [],
            "name": "",
            "rarity": 2,
            "tier": 1
          },
          {
            "character_id": "TFT15_Ashe",
            "itemNames": [
              "TFT_Item_RunaansHurricane",
              "TFT_Item_GuardianAngel",
              "TFT_Item_GuinsoosRageblade"
            ],
            "name": "",
            "rarity": 4,
            "tier": 2
          },
          {
            "character_id": "TFT15_KSante",
            "itemNames": [
              "TFT_Item_Artifact_TheIndomitable",
              "TFT_Item_GargoyleStoneplate",
              "TFT_Item_RedBuff"
            ],
            "name": "",
            "rarity": 4,
            "tier": 1
          },
          {
            "character_id": "TFT15_JarvanIV",
            "itemNames": [
              "TFT_Item_FrozenHeart",
              "TFT_Item_FrozenHeart"
            ],
            "name": "",
            "rarity": 4,
            "tier": 2
          },
          {
            "character_id": "TFT15_Braum",
            "itemNames": [],
            "name": "",
            "rarity": 6,
            "tier": 1
          },
          {
            "character_id": "tft15_leesin",
            "itemNames": [],
            "name": "",
            "rarity": 6,
            "tier": 1
          },
          {
            "character_id": "TFT15_Zyra",
            "itemNames": [
              "TFT_Item_JeweledGauntlet",
              "TFT15_Item_ChallengerEmblemItem"
            ],
            "name": "",
            "rarity": 6,
            "tier": 1
          },
          {
            "character_id": "TFT15_KSante",
            "itemNames": [],
            "name": "",
            "rarity": 4,
            "tier": 1
          }
        ],
        "win": false
      },
      {
        "companion": {
          "content_ID": "7704c9a7-d9d1-4059-a638-192a2b782aff",
          "item_ID": 77003,
          "skin_ID": 3,
          "species": "PetChibiMorgana"
        },
        "gold_left": 42,
        "last_round": 38,
        "level": 8,
        "missions": {
          "PlayerScore2": 219
        },
        "placement": 2,
        "players_eliminated": 3,
        "puuid": "Fch2j9cXT8lmqdnDmWd5An0m6-3zbUoAxNYhfF_jLk5xKEZ3bueretuZdFtqtY-WBmP3HJGgEbuMNg",
        "riotIdGameName": "PingPongKid",
        "riotIdTagline": "2000",
        "time_eliminated": 2198.039306640625,
        "total_damage_to_players": 169,
        "traits": [
          {
            "name": "TFT15_Bastion",
            "num_units": 2,
            "style": 1,
            "tier_current": 1,
            "tier_total": 3
          },
          {
            "name": "TFT15_BattleAcademia",
            "num_units": 7,
            "style": 4,
            "tier_current": 3,
            "tier_total": 4
          },
          {
            "name": "TFT15_Destroyer",
            "num_units": 2,
            "style": 1,
            "tier_current": 1,
            "tier_total": 4
          },
          {
            "name": "TFT15_Heavyweight",
            "num_units": 1,
            "style": 0,
            "tier_current": 0,
            "tier_total": 3
          },
          {
            "name": "TFT15_OldMentor",
            "num_units": 1,
            "style": 1,
            "tier_current": 1,
            "tier_total": 3
          },
          {
            "name": "TFT15_Prodigy",
            "num_units": 2,
            "style": 1,
            "tier_current": 1,
            "tier_total": 4
          },
          {
            "name": "TFT15_Protector",
            "num_units": 1,
            "style": 0,
            "tier_current": 0,
            "tier_total": 3
          },
          {
            "name": "TFT15_Strategist",
            "num_units": 1,
            "style": 0,
            "tier_current": 0,
            "tier_total": 4
          }
        ],
        "units": [
          {
            "character_id": "TFT15_Ezreal",
            "itemNames": [],
            "name": "",
            "rarity": 0,
            "tier": 2
          },
          {
            "character_id": "TFT15_Garen",
            "itemNames": [
              "TFT_Item_DragonsClaw",
              "TFT_Item_SteraksGage",
              "TFT_Item_NightHarvester"
            ],
            "name": "",
            "rarity": 0,
            "tier": 3
          },
          {
            "character_id": "TFT15_Rakan",
            "itemNames": [
              "TFT_Item_SteraksGage",
              "TFT_Item_WarmogsArmor",
              "TFT_Item_Redemption"
            ],
            "name": "",
            "rarity": 1,
            "tier": 3
          },
          {
            "character_id": "TFT15_Katarina",
            "itemNames": [
              "TFT_Item_UnstableConcoction",
              "TFT_Item_Artifact_Dawncore",
              "TFT_Item_GuardianAngel"
            ],
            "name": "",
            "rarity": 1,
            "tier": 3
          },
          {
            "character_id": "TFT15_Jayce",
            "itemNames": [],
            "name": "",
            "rarity": 2,
            "tier": 2
          },
          {
            "character_id": "TFT15_Leona",
            "itemNames": [
              "TFT_Item_GiantsBelt"
            ],
            "name": "",
            "rarity": 4,
            "tier": 2
          },
          {
            "character_id": "TFT15_Ryze",
            "itemNames": [],
            "name": "",
            "rarity": 4,
            "tier": 1
          },
          {
            "character_id": "TFT15_Yuumi",
            "itemNames": [
              "TFT_Item_HextechGunblade",
              "TFT_Item_StatikkShiv",
              "TFT_Item_RapidFireCannon"
            ],
            "name": "",
            "rarity": 4,
            "tier": 2
          }
        ],
        "win": true
      }
    ],
    "queueId": 1100,
    "queue_id": 1100,
    "tft_game_type": "standard",
    "tft_set_core_name": "TFTSet15",
    "tft_set_number": 15
  }
}