{
  "metadata": {
    "data_version": "6",
    "match_id": "NA1_5419580454",
    "participants": [
      "J5Y3GN_Hlle_bBhuNvN1QCczTEHtewxEEllyaRw7y0uhKYTJGzd_z0ZvpBrex3AlhwDVSfP6-ufzwQ",
      "Q3NALBVzlO3Obx1v8BXiIwaabve32wtZQzlTytQeQEljSdVgSXLv0rrv6k0tFKBoOisueJwct-jB2Q",
      "sq8aLroX3vBPrVnbHUB_g8fsuU5B925OhEoBVQu6jencDSH4uSxmk73K_wrWa4KRIeFzPFHacGRnDA",
      "ZrYRsqATUPzgGjDT24U-jVtj9vWonJMZgTX03j9JVUEx8c6qd07PxFMvmcZDWojPtqL9rTY841TD2w",
      "AwO-hfFyq81PFMMDtveorznfBd9-VoS3lJJ_IYA7g2xkX1TK86CPAiEwricaxcs05-c6aWDWt4thoA",
      "dkGTqGSvCvNL54ir8JExn0Rt-fQiaUcv9JJz_h-eVqzPoFgGKFaqS8sfGI5ycATf63-B8ktOn4pu9w",
      "lxO_1WKb5xAxt3JSMvtLZy39zDQd11iz9V_TU0TeiFGoWKEDcqWp_vEn7YAbCOGKUxY552_5ccGw5w",
      "ijm_CVkpeAKh6vPxh4MAi6DhiyqIdR5htOrHsF_9nUBqqjIFGVsQa3lA7YIlG-nJ_WfA1w6bvj-l5A"
    ]
  },
  "info": {
    "endOfGameResult": "GameComplete",
    "gameCreation": 1763871687000,
    "gameId": 5419580454,
    "game_datetime": 1763873646300,
    "game_length": 1855.365234375,
    "game_version": "Linux Version 15.23.728.3286 (Nov 21 2025/16:26:55) [PUBLIC] <Releases/15.23>",
    "mapId": 22,
    "participants": [
      {
        "companion": {
          "content_ID": "4d93f9fb-5123-4f86-8f1a-ccc164e9d368",
          "item_ID": 68003,
          "skin_ID": 3,
          "species": "PetChibiGwen"
        },
        "gold_left": 7,
        "last_round": 30,
        "level": 8,
        "missions": {
          "PlayerScore2": 92
        },
        "partner_group_id": 4,
        "placement": 5,
        "players_eliminated": 0,
        "puuid": "J5Y3GN_Hlle_bBhuNvN1QCczTEHtewxEEllyaRw7y0uhKYTJGzd_z0ZvpBrex3AlhwDVSfP6-ufzwQ",
        "riotIdGameName": "Your AngeI",
        "riotIdTagline": "NA1",
        "time_eliminated": 1846.854736328125,
        "total_damage_to_players": 41,
        "traits": [
          {
            "name": "TFT15_Destroyer",
            "num_units": 1,
            "style": 0,
            "tier_current": 0,
            "tier_total": 4
          },
          {
            "name": "TFT15_Duelist",
            "num_units": 1,
            "style": 0,
            "tier_current": 0,
            "tier_total": 3
          },
          {
            "name": "TFT15_Edgelord",
            "num_units": 2,
            "style": 1,
            "tier_current": 1,
            "tier_total": 3
          },
          {
            "name": "TFT15_Heavyweight",
            "num_units": 1,
            "style": 0,
            "tier_current": 0,
            "tier_total": 3
          },
          {
            "name": "TFT15_Juggernaut",
            "num_units": 1,
            "style": 0,
            "tier_current": 0,
            "tier_total": 3
          },
          {
            "name": "TFT15_Luchador",
            "num_units": 1,
            "style": 0,
            "tier_current": 0,
            "tier_total": 2
          },
          {
            "name": "TFT15_SentaiRanger",
            "num_units": 7,
            "style": 4,
            "tier_current": 3,
            "tier_total": 4
          },
          {
            "name": "TFT15_Spellslinger",
            "num_units": 2,
            "style": 1,
            "tier_current": 1,
            "tier_total": 3
          },
          {
            "name": "TFT15_Strategist",
            "num_units": 1,
            "style": 0,
            "tier_current": 0,
            "tier_total": 4
          }
        ],
        "units": [
          {
            "character_id": "TFT15_Lucian",
            "itemNames": [],
            "name": "",
            "rarity": 0,
            "tier": 1
          },
          {
            "character_id": "TFT15_Aatrox",
            "itemNames": [
              "TFT_Item_ThiefsGloves",
              "TFT_Item_JeweledGauntlet",
              "TFT_Item_ArchangelsStaff"
            ],
            "name": "",
            "rarity": 0,
            "tier": 2
          },
          {
            "character_id": "TFT15_Gangplank",
            "itemNames": [
              "TFT_Item_LastWhisper",
              "TFT_Item_InfinityEdge",
              "TFT_Item_Artifact_TheIndomitable"
            ],
            "name": "",
            "rarity": 1,
            "tier": 2
          },
          {
            "character_id": "TFT15_Senna",
            "itemNames": [
              "TFT_Item_ThiefsGloves",
              "TFT_Item_StatikkShiv",
              "TFT_Item_RapidFireCannon"
            ],
            "name": "",
            "rarity": 2,
            "tier": 2
          },
          {
            "character_id": "TFT15_Karma",
            "itemNames": [
              "TFT_Item_StatikkShiv",
              "TFT_Item_JeweledGauntlet",
              "TFT_Item_BlueBuff"
            ],
            "name": "",
            "rarity": 4,
            "tier": 2
          },
          {
            "character_id": "TFT15_JarvanIV",
            "itemNames": [
              "TFT_Item_FrozenHeart",
              "TFT_Item_RedBuff",
              "TFT_Item_SpectralGauntlet"
            ],
            "name": "",
            "rarity": 4,
            "tier": 2
          },
          {
            "character_id": "TFT15_Volibear",
            "itemNames": [
              "TFT_Item_SteraksGage",
              "TFT_Item_GuardianAngel",
              "TFT_Item_Bloodthirster"
            ],
            "name": "",
            "rarity": 4,
            "tier": 2
          },
          {
            "character_id": "TFT15_Yone",
            "itemNames": [
              "TFT_Item_ThiefsGloves",
              "TFT_Item_GuardianAngel",
              "TFT_Item_Deathblade"
            ],
            "name": "",
            "rarity": 6,
            "tier": 1
          },
          {
            "character_id": "TFT15_Galio",
            "itemNames": [
              "TFT15_RoboRanger_Core",
              "TFT15_RoboRanger_Sword",
              "TFT15_RoboRanger_Slicer"
            ],
            "name": "",
            "rarity": 9,
            "tier": 3
          }
        ],
        "win": false
      },
      {
        "companion": {
          "content_ID": "67b2e7fb-8402-4fcf-8410-d5cbc431a11a",
          "item_ID": 14028,
          "skin_ID": 28,
          "species": "PetQiyanaDog"
        },
        "gold_left": 8,
        "last_round": 30,
        "level": 9,
        "missions": {
          "PlayerScore2": 92
        },
        "partner_group_id": 4,
        "placement": 6,
        "players_eliminated": 1,
        "puuid": "Q3NALBVzlO3Obx1v8BXiIwaabve32wtZQzlTytQeQEljSdVgSXLv0rrv6k0tFKBoOisueJwct-jB2Q",
        "riotIdGameName": "gugam99",
        "riotIdTagline": "4014",
        "time_eliminated": 1845.25244140625,
        "total_damage_to_players": 32,
        "traits": [
          {
            "name": "TFT15_Bastion",
            "num_units": 1,
            "style": 0,
            "tier_current": 0,
            "tier_total": 3
          },
          {
            "name": "TFT15_Destroyer",
            "num_units": 1,
            "style": 0,
            "tier_current": 0,
            "tier_total": 4
          },
          {
            "name": "TFT15_Duelist",
            "num_units": 1,
            "style": 0,
            "tier_current": 0,
            "tier_total": 3
          },
          {
            "name": "TFT15_Edgelord",
            "num_units": 3,
            "style": 1,
            "tier_current": 1,
            "tier_total": 3
          },
          {
            "name": "TFT15_Juggernaut",
            "num_units": 2,
            "style": 1,
            "tier_current": 1,
            "tier_total": 3
          },
          {
            "name": "TFT15_Luchador",
            "num_units": 1,
            "style": 0,
            "tier_current": 0,
            "tier_total": 2
          },
          {
            "name": "TFT15_SoulFighter",
            "num_units": 8,
            "style": 4,
            "tier_current": 4,
            "tier_total": 5
          },
          {
            "name": "TFT15_Spellslinger",
            "num_units": 2,
            "style": 1,
            "tier_current": 1,
            "tier_total": 3
          }
        ],
        "units": [
          {
            "character_id": "TFT15_Kalista",
            "itemNames": [],
            "name": "",
            "rarity": 0,
            "tier": 2
          },
          {
            "character_id": "TFT15_Naafiri",
            "itemNames": [],
            "name": "",
            "rarity": 0,
            "tier": 2
          },
          {
            "character_id": "TFT15_Lux",
            "itemNames": [
              "TFT4_Item_OrnnTheCollector",
              "TFT_Item_JeweledGauntlet",
              "TFT_Item_RecurveBow"
            ],
            "name": "",
            "rarity": 1,
            "tier": 2
          },
          {
            "character_id": "TFT15_XinZhao",
            "itemNames": [
              "TFT_Item_NightHarvester",
              "TFT9_Item_OrnnHullbreaker",
              "TFT_Item_BrambleVest"
            ],
            "name": "",
            "rarity": 1,
            "tier": 2
          },
          {
            "character_id": "TFT15_Viego",
            "itemNames": [],
            "name": "",
            "rarity": 2,
            "tier": 2
          },
          {
            "character_id": "TFT15_Samira",
            "itemNames": [
              "TFT_Item_InfinityEdge",
              "TFT4_Item_OrnnTheCollector",
              "TFT_Item_LastWhisper"
            ],
            "name": "",
            "rarity": 4,
            "tier": 2
          },
          {
            "character_id": "TFT15_Sett",
            "itemNames": [
              "TFT_Item_BrambleVest",
              "TFT9_Item_OrnnHullbreaker",
              "TFT_Item_DragonsClaw"
            ],
            "name": "",
            "rarity": 4,
            "tier": 2
          },
          {
            "character_id": "TFT15_Volibear",
            "itemNames": [
              "TFT_Item_SteraksGage"
            ],
            "name": "",
            "rarity": 4,
            "tier": 1
          },
          {
            "character_id": "TFT15_Gwen",
            "itemNames": [
              "TFT4_Item_OrnnDeathsDefiance",
              "TFT_Item_JeweledGauntlet",
              "TFT_Item_StatikkShiv"
            ],
            "name": "",
            "rarity": 6,
            "tier": 2
          }
        ],
        "win": false
      },
      {
        "companion": {
          "content_ID": "8a5a8621-64f6-42d4-81a3-dd7b606ed08f",
          "item_ID": 68001,
          "skin_ID": 1,
          "species": "PetChibiGwen"
        },
        "gold_left": 1,
        "last_round": 30,
        "level": 9,
        "missions": {
          "PlayerScore2": 184
        },
        "partner_group_id": 3,
        "placement": 2,
        "players_eliminated": 3,
        "puuid": "sq8aLroX3vBPrVnbHUB_g8fsuU5B925OhEoBVQu6jencDSH4uSxmk73K_wrWa4KRIeFzPFHacGRnDA",
        "riotIdGameName": "SweetTangie",
        "riotIdTagline": "420",
        "time_eliminated": 1847.1051025390625,
        "total_damage_to_players": 80,
        "traits": [
          {
            "name": "TFT15_BattleAcademia",
            "num_units": 1,
            "style": 0,
            "tier_current": 0,
            "tier_total": 4
          },
          {
            "name": "TFT15_Captain",
            "num_units": 1,
            "style": 3,
            "tier_current": 1,
            "tier_total": 1
          },
          {
            "name": "TFT15_Destroyer",
            "num_units": 1,
            "style": 0,
            "tier_current": 0,
            "tier_total": 4
          },
          {
            "name": "TFT15_Empyrean",
            "num_units": 1,
            "style": 0,
            "tier_current": 0,
            "tier_total": 3
          },
          {
            "name": "TFT15_GemForce",
            "num_units": 1,
            "style": 0,
            "tier_current": 0,
            "tier_total": 4
          },
          {
            "name": "TFT15_OldMentor",
            "num_units": 1,
            "style": 1,
            "tier_current": 1,
            "tier_total": 3
          },
          {
            "name": "TFT15_Protector",
            "num_units": 6,
            "style": 4,
            "tier_current": 3,
            "tier_total": 3
          },
          {
            "name": "TFT15_Sniper",
            "num_units": 1,
            "style": 0,
            "tier_current": 0,
            "tier_total": 4
          },
          {
            "name": "TFT15_Spellslinger",
            "num_units": 1,
            "style": 0,
            "tier_current": 0,
            "tier_total": 3
          },
          {
            "name": "TFT15_StarGuardian",
            "num_units": 2,
            "style": 1,
            "tier_current": 1,
            "tier_total": 12
          },
          {
            "name": "TFT15_Strategist",
            "num_units": 2,
            "style": 1,
            "tier_current": 1,
            "tier_total": 4
          },
          {
            "name": "TFT15_SupremeCells",
            "num_units": 1,
            "style": 0,
            "tier_current": 0,
            "tier_total": 3
          },
          {
            "name": "TFT15_TheCrew",
            "num_units": 2,
            "style": 1,
            "tier_current": 7,
            "tier_total": 7
          }
        ],
        "units": [
          {
            "character_id": "TFT15_Kennen",
            "itemNames": [
              "TFT_Item_RecurveBow"
            ],
            "name": "",
            "rarity": 0,
            "tier": 2
          },
          {
            "character_id": "TFT15_Malphite",
            "itemNames": [],
            "name": "",
            "rarity": 0,
            "tier": 2
          },
          {
            "character_id": "TFT15_Rakan",
            "itemNames": [
              "TFT_Item_ThiefsGloves",
              "TFT_Item_NightHarvester",
              "TFT_Item_GargoyleStoneplate"
            ],
            "name": "",
            "rarity": 1,
            "tier": 2
          },
          {
            "character_id": "TFT15_Janna",
            "itemNames": [],
            "name": "",
            "rarity": 1,
            "tier": 2
          },
          {
            "character_id": "TFT15_Neeko",
            "itemNames": [
              "TFT_Item_RedBuff",
              "TFT_Item_IonicSpark",
              "TFT7_Item_ShimmerscaleMogulsMail"
            ],
            "name": "",
            "rarity": 2,
            "tier": 2
          },
          {
            "character_id": "TFT15_Jinx",
            "itemNames": [],
            "name": "",
            "rarity": 4,
            "tier": 1
          },
          {
            "character_id": "TFT15_KSante",
            "itemNames": [
              "TFT_Item_Bloodthirster",
              "TFT_Item_GuardianAngel",
              "TFT_Item_Artifact_TitanicHydra"
            ],
            "name": "",
            "rarity": 4,
            "tier": 2
          },
          {
            "character_id": "TFT15_Ryze",
            "itemNames": [
              "TFT_Item_SpearOfShojin",
              "TFT_Item_AdaptiveHelm"
            ],
            "name": "",
            "rarity": 4,
            "tier": 2
          },
          {
            "character_id": "TFT15_TwistedFate",
            "itemNames": [
              "TFT_Item_GuinsoosRageblade",
              "TFT_Item_GuinsoosRageblade",
              "TFT7_Item_ShimmerscaleGamblersBlade"
            ],
            "name": "",
            "rarity": 6,
            "tier": 2
          }
        ],
        "win": true
      },
      {
        "companion": {
          "content_ID": "8a5a8621-64f6-42d4-81a3-dd7b606ed08f",
          "item_ID": 68001,
          "skin_ID": 1,
          "species": "PetChibiGwen"
        },
        "gold_left": 2,
        "last_round": 30,
        "level": 9,
        "missions": {
          "PlayerScore2": 184
        },
        "partner_group_id": 3,
        "placement": 1,
        "players_eliminated": 1,
        "puuid": "ZrYRsqATUPzgGjDT24U-jVtj9vWonJMZgTX03j9JVUEx8c6qd07PxFMvmcZDWojPtqL9rTY841TD2w",
        "riotIdGameName": "JFORD",
        "riotIdTagline": "420",
        "time_eliminated": 1847.1051025390625,
        "total_damage_to_players": 90,
        "traits": [
          {
            "name": "TFT15_Bastion",
            "num_units": 2,
            "style": 1,
            "tier_current": 1,
            "tier_total": 3
          },
          {
            "name": "TFT15_Destroyer",
            "num_units": 1,
            "style": 0,
            "tier_current": 0,
            "tier_total": 4
          },
          {
            "name": "TFT15_DragonFist",
            "num_units": 1,
            "style": 3,
            "tier_current": 1,
            "tier_total": 1
          },
          {
            "name": "TFT15_Duelist",
            "num_units": 1,
            "style": 0,
            "tier_current": 0,
            "tier_total": 3
          },
          {
            "name": "TFT15_ElTigre",
            "num_units": 1,
            "style": 3,
            "tier_current": 1,
            "tier_total": 1
          },
          {
            "name": "TFT15_Empyrean",
            "num_units": 1,
            "style": 0,
            "tier_current": 0,
            "tier_total": 3
          },
          {
            "name": "TFT15_GemForce",
            "num_units": 7,
            "style": 4,
            "tier_current": 3,
            "tier_total": 4
          },
          {
            "name": "TFT15_Juggernaut",
            "num_units": 2,
            "style": 1,
            "tier_current": 1,
            "tier_total": 3
          },
          {
            "name": "TFT15_Luchador",
            "num_units": 1,
            "style": 0,
            "tier_current": 0,
            "tier_total": 2
          },
          {
            "name": "TFT15_OldMentor",
            "num_units": 1,
            "style": 1,
            "tier_current": 1,
            "tier_total": 3
          },
          {
            "name": "TFT15_Protector",
            "num_units": 2,
            "style": 1,
            "tier_current": 1,
            "tier_total": 3
          },
          {
            "name": "TFT15_Rosemother",
            "num_units": 1,
            "style": 3,
            "tier_current": 1,
            "tier_total": 1
          },
          {
            "name": "TFT15_SentaiRanger",
            "num_units": 1,
            "style": 0,
            "tier_current": 0,
            "tier_total": 4
          },
          {
            "name": "TFT15_Spellslinger",
            "num_units": 1,
            "style": 0,
            "tier_current": 0,
            "tier_total": 3
          },
          {
            "name": "TFT15_Strategist",
            "num_units": 5,
            "style": 4,
            "tier_current": 4,
            "tier_total": 4
          }
        ],
        "units": [
          {
            "character_id": "TFT15_Vi",
            "itemNames": [
              "TFT_Item_ThiefsGloves",
              "TFT_Item_EmptyBag",
              "TFT_Item_EmptyBag"
            ],
            "name": "",
            "rarity": 1,
            "tier": 2
          },
          {
            "character_id": "TFT15_Janna",
            "itemNames": [],
            "name": "",
            "rarity": 1,
            "tier": 1
          },
          {
            "character_id": "TFT15_Swain",
            "itemNames": [
              "TFT_Item_FrozenHeart",
              "TFT15_Item_ShotcallerEmblemItem"
            ],
            "name": "",
            "rarity": 2,
            "tier": 2
          },
          {
            "character_id": "TFT15_Ashe",
            "itemNames": [
              "TFT_Item_GuinsoosRageblade",
              "TFT_Item_RunaansHurricane",
              "TFT_Item_MadredsBloodrazor"
            ],
            "name": "",
            "rarity": 4,
            "tier": 2
          },
          {
            "character_id": "TFT15_KSante",
            "itemNames": [
              "TFT_Item_SpectralGauntlet",
              "TFT_Item_DragonsClaw"
            ],
            "name": "",
            "rarity": 4,
            "tier": 1
          },
          {
            "character_id": "TFT15_Ryze",
            "itemNames": [
              "TFT_Item_ForceOfNature"
            ],
            "name": "",
            "rarity": 4,
            "tier": 1
          },
          {
            "character_id": "TFT15_JarvanIV",
            "itemNames": [
              "TFT5_Item_ThiefsGlovesRadiant",
              "TFT_Item_EmptyBag",
              "TFT_Item_EmptyBag"
            ],
            "name": "",
            "rarity": 4,
            "tier": 1
          },
          {
            "character_id": "TFT15_Braum",
            "itemNames": [
              "TFT_Item_SteraksGage",
              "TFT15_Item_CrystalRoseEmblemItem",
              "TFT_Item_Bloodthirster"
            ],
            "name": "",
            "rarity": 6,
            "tier": 2
          },
          {
            "character_id": "tft15_leesin",
            "itemNames": [
              "TFT_Item_InfinityEdge",
              "TFT15_Item_CrystalRoseEmblemItem",
              "TFT_Item_UnstableConcoction"
            ],
            "name": "",
            "rarity": 6,
            "tier": 2
          },
          {
            "character_id": "TFT15_Zyra",
            "itemNames": [
              "TFT15_Item_ShotcallerEmblemItem",
              "TFT_Item_RapidFireCannon",
              "TFT_Item_AdaptiveHelm"
            ],
            "name": "",
            "rarity": 6,
            "tier": 2
          }
        ],
        "win": true
      },
      {
        "companion": {
          "content_ID": "bf219e7b-66f8-417e-8208-c867ccdcb10c",
          "item_ID": 74001,
          "skin_ID": 1,
          "species": "PetChibiIrelia"
        },
        "gold_left": 1,
        "last_round": 27,
        "level": 8,
        "missions": {
          "PlayerScore2": 83
        },
        "partner_group_id": 1,
        "placement": 8,
        "players_eliminated": 0,
        "puuid": "AwO-hfFyq81PFMMDtveorznfBd9-VoS3lJJ_IYA7g2xkX1TK86CPAiEwricaxcs05-c6aWDWt4thoA",
        "riotIdGameName": "BiBi CmaL",
        "riotIdTagline": "NA1",
        "time_eliminated": 1644.992919921875,
        "total_damage_to_players": 14,
        "traits": [
          {
            "name": "TFT15_Bastion",
            "num_units": 1,
            "style": 0,
            "tier_current": 0,
            "tier_total": 3
          },
          {
            "name": "TFT15_BattleAcademia",
            "num_units": 1,
            "style": 0,
            "tier_current": 0,
            "tier_total": 4
          },
          {
            "name": "TFT15_Destroyer",
            "num_units": 1,
            "style": 0,
            "tier_current": 0,
            "tier_total": 4
          },
          {
            "name": "TFT15_Duelist",
            "num_units": 1,
            "style": 0,
            "tier_current": 0,
            "tier_total": 3
          },
          {
            "name": "TFT15_Edgelord",
            "num_units": 4,
            "style": 2,
            "tier_current": 2,
            "tier_total": 3
          },
          {
            "name": "TFT15_Juggernaut",
            "num_units": 3,
            "style": 1,
            "tier_current": 1,
            "tier_total": 3
          },
          {
            "name": "TFT15_Luchador",
            "num_units": 2,
            "style": 1,
            "tier_current": 1,
            "tier_total": 2
          },
          {
            "name": "TFT15_OldMentor",
            "num_units": 1,
            "style": 1,
            "tier_current": 1,
            "tier_total": 3
          },
          {
            "name": "TFT15_SentaiRanger",
            "num_units": 1,
            "style": 0,
            "tier_current": 0,
            "tier_total": 4
          },
          {
            "name": "TFT15_Sniper",
            "num_units": 1,
            "style": 0,
            "tier_current": 0,
            "tier_total": 4
          },
          {
            "name": "TFT15_SoulFighter",
            "num_units": 4,
            "style": 2,
            "tier_current": 2,
            "tier_total": 5
          },
          {
            "name": "TFT15_StarGuardian",
            "num_units": 1,
            "style": 0,
            "tier_current": 0,
            "tier_total": 12
          },
          {
            "name": "TFT15_Strategist",
            "num_units": 1,
            "style": 0,
            "tier_current": 0,
            "tier_total": 4
          }
        ],
        "units": [
          {
            "character_id": "TFT15_Rell",
            "itemNames": [
              "TFT_Item_BrambleVest",
              "TFT_Item_IonicSpark",
              "TFT15_Item_JuggernautEmblemItem"
            ],
            "name": "",
            "rarity": 0,
            "tier": 3
          },
          {
            "character_id": "TFT15_DrMundo",
            "itemNames": [],
            "name": "",
            "rarity": 1,
            "tier": 1
          },
          {
            "character_id": "TFT15_Viego",
            "itemNames": [],
            "name": "",
            "rarity": 2,
            "tier": 1
          },
          {
            "character_id": "TFT15_Ryze",
            "itemNames": [
              "TFT15_Item_BattleAcademiaEmblemItem",
              "TFT15_Item_SoulFighterEmblemItem"
            ],
            "name": "",
            "rarity": 4,
            "tier": 2
          },
          {
            "character_id": "TFT15_Samira",
            "itemNames": [],
            "name": "",
            "rarity": 4,
            "tier": 1
          },
          {
            "character_id": "TFT15_Sett",
            "itemNames": [
              "TFT_Item_GiantsBelt"
            ],
            "name": "",
            "rarity": 4,
            "tier": 2
          },
          {
            "character_id": "TFT15_Volibear",
            "itemNames": [
              "TFT_Item_InfinityEdge",
              "TFT_Item_PowerGauntlet",
              "TFT_Item_TitansResolve"
            ],
            "name": "",
            "rarity": 4,
            "tier": 1
          },
          {
            "character_id": "TFT15_Yone",
            "itemNames": [
              "TFT_Item_InfinityEdge",
              "TFT15_Item_SniperEmblemItem",
              "TFT_Item_SpearOfShojin"
            ],
            "name": "",
            "rarity": 6,
            "tier": 2
          }
        ],
        "win": false
      },
      {
        "companion": {
          "content_ID": "c6597cc8-c9b4-4466-832b-85684df3800c",
          "item_ID": 79003,
          "skin_ID": 3,
          "species": "PetChibiYone"
        },
        "gold_left": 1,
        "last_round": 27,
        "level": 8,
        "missions": {
          "PlayerScore2": 83
        },
        "partner_group_id": 1,
        "placement": 7,
        "players_eliminated": 0,
        "puuid": "dkGTqGSvCvNL54ir8JExn0Rt-fQiaUcv9JJz_h-eVqzPoFgGKFaqS8sfGI5ycATf63-B8ktOn4pu9w",
        "riotIdGameName": "PiPi Bird",
        "riotIdTagline": "NA1",
        "time_eliminated": 1668.02392578125,
        "total_damage_to_players": 40,
        "traits": [
          {
            "name": "TFT15_Bastion",
            "num_units": 1,
            "style": 0,
            "tier_current": 0,
            "tier_total": 3
          },
          {
            "name": "TFT15_Duelist",
            "num_units": 1,
            "style": 0,
            "tier_current": 0,
            "tier_total": 3
          },
          {
            "name": "TFT15_Edgelord",
            "num_units": 3,
            "style": 1,
            "tier_current": 1,
            "tier_total": 3
          },
          {
            "name": "TFT15_Juggernaut",
            "num_units": 2,
            "style": 1,
            "tier_current": 1,
            "tier_total": 3
          },
          {
            "name": "TFT15_Luchador",
            "num_units": 1,
            "style": 0,
            "tier_current": 0,
            "tier_total": 2
          },
          {
            "name": "TFT15_SoulFighter",
            "num_units": 7,
            "style": 2,
            "tier_current": 3,
            "tier_total": 5
          },
          {
            "name": "TFT15_Spellslinger",
            "num_units": 2,
            "style": 1,
            "tier_current": 1,
            "tier_total": 3
          }
        ],
        "units": [
          {
            "character_id": "TFT15_Naafiri",
            "itemNames": [
              "TFT_Item_ThiefsGloves",
              "TFT_Item_RapidFireCannon",
              "TFT_Item_Bloodthirster"
            ],
            "name": "",
            "rarity": 0,
            "tier": 2
          },
          {
            "character_id": "TFT15_Lux",
            "itemNames": [
              "TFT_Item_ThiefsGloves",
              "TFT_Item_EmptyBag",
              "TFT_Item_EmptyBag"
            ],
            "name": "",
            "rarity": 1,
            "tier": 2
          },
          {
            "character_id": "TFT15_XinZhao",
            "itemNames": [
              "TFT_Item_ThiefsGloves",
              "TFT_Item_Morellonomicon",
              "TFT_Item_RedBuff"
            ],
            "name": "",
            "rarity": 1,
            "tier": 2
          },
          {
            "character_id": "TFT15_Viego",
            "itemNames": [],
            "name": "",
            "rarity": 2,
            "tier": 2
          },
          {
            "character_id": "TFT15_Samira",
            "itemNames": [
              "TFT_Item_InfinityEdge",
              "TFT4_Item_OrnnInfinityForce",
              "TFT_Item_PowerGauntlet"
            ],
            "name": "",
            "rarity": 4,
            "tier": 2
          },
          {
            "character_id": "TFT15_Sett",
            "itemNames": [
              "TFT_Item_GargoyleStoneplate",
              "TFT_Item_Redemption",
              "TFT_Item_Artifact_TheIndomitable"
            ],
            "name": "",
            "rarity": 4,
            "tier": 2
          },
          {
            "character_id": "TFT15_Volibear",
            "itemNames": [
              "TFT_Item_GuardianAngel",
              "TFT_Item_InfinityEdge",
              "TFT_Item_UnstableConcoction"
            ],
            "name": "",
            "rarity": 4,
            "tier": 1
          },
          {
            "character_id": "TFT15_Gwen",
            "itemNames": [
              "TFT_Item_JeweledGauntlet",
              "TFT_Item_GuardianAngel",
              "TFT_Item_Morellonomicon"
            ],
            "name": "",
            "rarity": 6,
            "tier": 1
          }
        ],
        "win": false
      },
      {
        "companion": {
          "content_ID": "7704c9a7-d9d1-4059-a638-192a2b782aff",
          "item_ID": 77003,
          "skin_ID": 3,
          "species": "PetChibiMorgana"
        },
        "gold_left": 24,
        "last_round": 30,
        "level": 8,
        "missions": {
          "PlayerScore2": 184
        },
        "partner_group_id": 2,
        "placement": 4,
        "players_eliminated": 1,
        "puuid": "lxO_1WKb5xAxt3JSMvtLZy39zDQd11iz9V_TU0TeiFGoWKEDcqWp_vEn7YAbCOGKUxY552_5ccGw5w",
        "riotIdGameName": "chulie",
        "riotIdTagline": "uwu",
        "time_eliminated": 1839.5946044921875,
        "total_damage_to_players": 41,
        "traits": [
          {
            "name": "TFT15_Bastion",
            "num_units": 1,
            "style": 0,
            "tier_current": 0,
            "tier_total": 3
          },
          {
            "name": "TFT15_Empyrean",
            "num_units": 1,
            "style": 0,
            "tier_current": 0,
            "tier_total": 3
          },
          {
            "name": "TFT15_GemForce",
            "num_units": 1,
            "style": 0,
            "tier_current": 0,
            "tier_total": 4
          },
          {
            "name": "TFT15_Heavyweight",
            "num_units": 2,
            "style": 1,
            "tier_current": 1,
            "tier_total": 3
          },
          {
            "name": "TFT15_OldMentor",
            "num_units": 1,
            "style": 1,
            "tier_current": 1,
            "tier_total": 3
          },
          {
            "name": "TFT15_Prodigy",
            "num_units": 2,
            "style": 1,
            "tier_current": 1,
            "tier_total": 4
          },
          {
            "name": "TFT15_Protector",
            "num_units": 2,
            "style": 1,
            "tier_current": 1,
            "tier_total": 3
          },
          {
            "name": "TFT15_Sniper",
            "num_units": 1,
            "style": 0,
            "tier_current": 0,
            "tier_total": 4
          },
          {
            "name": "TFT15_StarGuardian",
            "num_units": 7,
            "style": 4,
            "tier_current": 6,
            "tier_total": 12
          }
        ],
        "units": [
          {
            "character_id": "TFT15_Rell",
            "itemNames": [],
            "name": "",
            "rarity": 0,
            "tier": 2
          },
          {
            "character_id": "TFT15_Syndra",
            "itemNames": [
              "TFT_Item_MadredsBloodrazor",
              "TFT_Item_StatikkShiv",
              "TFT_Item_RabadonsDeathcap"
            ],
            "name": "",
            "rarity": 0,
            "tier": 2
          },
          {
            "character_id": "TFT15_Kobuko",
            "itemNames": [
              "TFT15_Item_StarGuardianEmblemItem"
            ],
            "name": "",
            "rarity": 1,
            "tier": 2
          },
          {
            "character_id": "TFT15_Neeko",
            "itemNames": [],
            "name": "",
            "rarity": 2,
            "tier": 2
          },
          {
            "character_id": "TFT15_Jinx",
            "itemNames": [
              "TFT7_Item_ShimmerscaleGamblersBlade",
              "TFT_Item_SpearOfShojin",
              "TFT_Item_InfinityEdge"
            ],
            "name": "",
            "rarity": 4,
            "tier": 2
          },
          {
            "character_id": "TFT15_KSante",
            "itemNames": [
              "TFT_Item_Artifact_TalismanOfAscension",
              "TFT_Item_AdaptiveHelm",
              "TFT_Item_FrozenHeart"
            ],
            "name": "",
            "rarity": 4,
            "tier": 2
          },
          {
            "character_id": "TFT15_Poppy",
            "itemNames": [
              "TFT_Item_Redemption",
              "TFT_Item_GargoyleStoneplate",
              "TFT7_Item_ShimmerscaleMogulsMail"
            ],
            "name": "",
            "rarity": 4,
            "tier": 2
          },
          {
            "character_id": "TFT15_Seraphine",
            "itemNames": [
              "TFT_Item_Morellonomicon",
              "TFT_Item_RabadonsDeathcap"
            ],
            "name": "",
            "rarity": 6,
            "tier": 1
          }
        ],
        "win": true
      },
      {
        "companion": {
          "content_ID": "b717a3ed-8086-4ed6-82f3-78120dc98ab7",
          "item_ID": 87002,
          "skin_ID": 2,
          "species": "PetChibiBlitzcrank"
        },
        "gold_left": 14,
        "last_round": 30,
        "level": 8,
        "missions": {
          "PlayerScore2": 184
        },
        "partner_group_id": 2,
        "placement": 3,
        "players_eliminated": 1,
        "puuid": "ijm_CVkpeAKh6vPxh4MAi6DhiyqIdR5htOrHsF_9nUBqqjIFGVsQa3lA7YIlG-nJ_WfA1w6bvj-l5A",
        "riotIdGameName": "Carryion",
        "riotIdTagline": "NA1",
        "time_eliminated": 1847.1051025390625,
        "total_damage_to_players": 32,
        "traits": [
          {
            "name": "TFT15_Bastion",
            "num_units": 1,
            "style": 0,
            "tier_current": 0,
            "tier_total": 3
          },
          {
            "name": "TFT15_Captain",
            "num_units": 1,
            "style": 3,
            "tier_current": 1,
            "tier_total": 1
          },
          {
            "name": "TFT15_Destroyer",
            "num_units": 1,
            "style": 0,
            "tier_current": 0,
            "tier_total": 4
          },
          {
            "name": "TFT15_Edgelord",
            "num_units": 1,
            "style": 0,
            "tier_current": 0,
            "tier_total": 3
          },
          {
            "name": "TFT15_GemForce",
            "num_units": 1,
            "style": 0,
            "tier_current": 0,
            "tier_total": 4
          },
          {
            "name": "TFT15_OldMentor",
            "num_units": 1,
            "style": 1,
            "tier_current": 1,
            "tier_total": 3
          },
          {
            "name": "TFT15_Protector",
            "num_units": 2,
            "style": 1,
            "tier_current": 1,
            "tier_total": 3
          },
          {
            "name": "TFT15_SentaiRanger",
            "num_units": 1,
            "style": 0,
            "tier_current": 0,
            "tier_total": 4
          },
          {
            "name": "TFT15_Sniper",
            "num_units": 1,
            "style": 0,
            "tier_current": 0,
            "tier_total": 4
          },
          {
            "name": "TFT15_Strategist",
            "num_units": 4,
            "style": 4,
            "tier_current": 3,
            "tier_total": 4
          },
          {
            "name": "TFT15_TheCrew",
            "num_units": 5,
            "style": 1,
            "tier_current": 7,
            "tier_total": 7
          }
        ],
        "units": [
          {
            "character_id": "TFT15_Sivir",
            "itemNames": [
              "TFT_Item_Deathblade",
              "TFT_Item_PowerGauntlet",
              "TFT_Item_LastWhisper"
            ],
            "name": "",
            "rarity": 0,
            "tier": 3
          },
          {
            "character_id": "TFT15_Malphite",
            "itemNames": [
              "TFT_Item_WarmogsArmor",
              "TFT_Item_GargoyleStoneplate",
              "TFT_Item_Redemption"
            ],
            "name": "",
            "rarity": 0,
            "tier": 3
          },
          {
            "character_id": "TFT15_Shen",
            "itemNames": [
              "TFT_Item_IonicSpark"
            ],
            "name": "",
            "rarity": 1,
            "tier": 3
          },
          {
            "character_id": "TFT15_Janna",
            "itemNames": [
              "TFT_Item_StatikkShiv",
              "TFT_Item_ArchangelsStaff",
              "TFT_Item_NeedlesslyLargeRod"
            ],
            "name": "",
            "rarity": 1,
            "tier": 3
          },
          {
            "character_id": "TFT15_Ziggs",
            "itemNames": [
              "TFT_Item_Artifact_BlightingJewel",
              "TFT_Item_GuinsoosRageblade",
              "TFT_Item_MadredsBloodrazor"
            ],
            "name": "",
            "rarity": 2,
            "tier": 3
          },
          {
            "character_id": "TFT15_Ryze",
            "itemNames": [],
            "name": "",
            "rarity": 4,
            "tier": 2
          },
          {
            "character_id": "TFT15_JarvanIV",
            "itemNames": [],
            "name": "",
            "rarity": 4,
            "tier": 2
          },
          {
            "character_id": "TFT15_TwistedFate",
            "itemNames": [],
            "name": "",
            "rarity": 6,
            "tier": 1
          }
        ],
        "win": true
      }
    ],
    "queueId": 1160,
    "queue_id": 1160,
    "tft_game_type": "pairs",
    "tft_set_core_name": "TFTSet15",
    "tft_set_number": 15
  }
}